svg_helpers/__init__.py
svg_helpers/element.py
svg_helpers/shapely_helpers.py
svg_helpers-0.3.0.dist-info/LICENSE
svg_helpers-0.3.0.dist-info/METADATA
svg_helpers-0.3.0.dist-info/WHEEL
svg_helpers-0.3.0.dist-info/RECORD
