Metadata-Version: 2.1
Name: svg-helpers
Version: 0.3.0
Summary: 
Author: stringertheory
Author-email: mike.stringer.internet@gmail.com
Requires-Python: >=3.9,<4.0
Classifier: Programming Language :: Python :: 3
Classifier: Programming Language :: Python :: 3.9
Classifier: Programming Language :: Python :: 3.10
Classifier: Programming Language :: Python :: 3.11
Classifier: Programming Language :: Python :: 3.12
Requires-Dist: lxml (>=5.1.0,<6.0.0)
